HoughVG/Fingerprint.py
HoughVG/HoughLine.py
HoughVG/HoughLineParallel.py
HoughVG/__init__.py
HoughVG/__main__.py
houghvg-0.1.1.dist-info/licenses/LICENSE
houghvg-0.1.1.dist-info/METADATA
houghvg-0.1.1.dist-info/WHEEL
houghvg-0.1.1.dist-info/top_level.txt
houghvg-0.1.1.dist-info/RECORD
