Metadata-Version: 2.4
Name: houghvg
Version: 0.1.1
Summary: Une boîte à outils de la Transformée de Hough basée sur les grilles virtuelles
Author-email: Moïse Ouedraogo <moisewedra@gmail.com>
License: MIT
Project-URL: Homepage, https://github.com/moise-github/houghvg
Requires-Python: >=3.7
License-File: LICENSE
Requires-Dist: numpy>=1.24.2
Requires-Dist: opencv-contrib-python>=4.7.0.72
Requires-Dist: pymp-pypi>=0.5.0
Requires-Dist: matplotlib>=3.6.3
Requires-Dist: scipy>=1.10.1
Requires-Dist: scikit-image>=0.21.0
Dynamic: license-file
